[
  {
    "name": "DON'T PLAY",
    "artist": "Turnstile",
    "url": "https://open.spotify.com/track/69uzV9BQmNLPIu0dWK4Tbe",
    "image": "https://i.scdn.co/image/ab67616d0000b273c11ba539d58741bbd1332c92",
    "preview_url": null
  },
  {
    "name": "I CARE",
    "artist": "Turnstile",
    "url": "https://open.spotify.com/track/7KVIuHxbV5lvBE5Vyiw8FC",
    "image": "https://i.scdn.co/image/ab67616d0000b273e6b88d3e4886ae3a17621c53",
    "preview_url": null
  },
  {
    "name": "Love Is an Open Door - From \"Frozen\"/Soundtrack Version",
    "artist": "Kristen Bell, Santino Fontana",
    "url": "https://open.spotify.com/track/3IPnBzGRMg6BfViFxxa0Gq",
    "image": "https://i.scdn.co/image/ab67616d0000b273a985e1e7c6b095da213eaa7c",
    "preview_url": null
  },
  {
    "name": "Zero To Hero",
    "artist": "Chorus - Hercules, Lillias White, Cheryl Freeman, LaChanze, Roz Ryan, Vaneese Thomas, Tawatha Agee, Disney",
    "url": "https://open.spotify.com/track/4zDfgax6Ihb0UWdour1ZEs",
    "image": "https://i.scdn.co/image/ab67616d0000b273f6a713be4f418307ab7ffaf4",
    "preview_url": null
  },
  {
    "name": "You're Welcome",
    "artist": "Dwayne Johnson, Disney",
    "url": "https://open.spotify.com/track/6U4VqEHy4n5VeiH4pQPL24",
    "image": "https://i.scdn.co/image/ab67616d0000b273b30f2e44ae6fa43305bd00bf",
    "preview_url": null
  }
]